fixdate.py
fixdate-2.1.0.dist-info/METADATA
fixdate-2.1.0.dist-info/WHEEL
fixdate-2.1.0.dist-info/licenses/LICENSE.txt
fixdate-2.1.0.dist-info/RECORD
