Metadata-Version: 2.4
Name: FixDate
Version: 2.1.0
Summary: Fix a date and present it in specified format.
License-Expression: MIT
License-File: LICENSE.txt
Author: Hendrik du Toit
Author-email: hendrik@brightedge.co.za
Maintainer: Hendrik du Toit
Maintainer-email: hendrikdt@citiqprepaid.co.za
Requires-Python: >=3.10
Classifier: Development Status :: 5 - Production/Stable
Classifier: Intended Audience :: Developers
Classifier: Intended Audience :: Information Technology
Classifier: Intended Audience :: System Administrators
Classifier: License :: OSI Approved :: MIT License
Classifier: Programming Language :: Python :: 3.10
Classifier: Programming Language :: Python :: 3.11
Classifier: Programming Language :: Python :: 3.12
Classifier: Programming Language :: Python :: 3.13
Classifier: Topic :: Software Development :: Libraries :: Python Modules
Classifier: Topic :: System :: Archiving :: Packaging
Project-URL: Homepage, https://github.com/BrightEdgeeServices/FixDate
Project-URL: Issues, https://github.com/BrightEdgeeServices/FixDate/issues
Project-URL: Repository, https://github.com/BrightEdgeeServices/FixDate.git
Project-URL: changelog, https://github.com/BrightEdgeeServices/FixDate/releases
